lvmcam/__init__.py
lvmcam/__main__.py
lvmcam/camera.py
lvmcam/exceptions.py
lvmcam/actor/__init__.py
lvmcam/actor/actor.py
lvmcam/actor/commands/__init__.py
lvmcam/actor/commands/gain.py
lvmcam/actor/commands/reconnect.py
lvmcam/etc/lvm.camera_param.agcam.yml
lvmcam/etc/lvm.sci.agcam.yml
lvmcam/etc/lvm.skye.agcam.yml
lvmcam/etc/lvm.skyw.agcam.yml
lvmcam/etc/lvm.spec.agcam.yml
lvmcam/models/__init__.py
lvmcam/models/camera.py
lvmcam/models/genicam.py
lvmcam/models/proc.py
lvmcam/models/scraper.py
lvmcam/models/wcs.py
sdss_lvmcam-1.1.3.dist-info/METADATA
sdss_lvmcam-1.1.3.dist-info/WHEEL
sdss_lvmcam-1.1.3.dist-info/entry_points.txt
sdss_lvmcam-1.1.3.dist-info/licenses/LICENSE.md
sdss_lvmcam-1.1.3.dist-info/RECORD
