Metadata-Version: 2.4
Name: sdss-lvmcam
Version: 1.1.3
Summary: The package for lvmcam
Project-URL: Homepage, https://github.com/sdss/lvmcam
Project-URL: Repository, https://github.com/sdss/lvmcam
Project-URL: Documentation, https://sdss-lvmcam.readthedocs.org
Author-email: Florian Briegel <briegel@mpia.de>, "Richard J. Mathar" <mathar@mpia.de>
Maintainer-email: Florian Briegel <briegel@mpia.de>, José Sánchez-Gallego <gallegoj@uw.edu>
License-Expression: BSD-3-Clause
License-File: LICENSE.md
Requires-Python: <4,>=3.10
Requires-Dist: numpy==1.26.4
Requires-Dist: pygobject==3.48.2
Requires-Dist: sdss-basecam>=0.8.2
Requires-Dist: sdss-lvmtipo>=0.2.0
